fastlangml/__init__.py
fastlangml/backends/__init__.py
fastlangml/backends/base.py
fastlangml/backends/fastlangid_backend.py
fastlangml/backends/fasttext_backend.py
fastlangml/backends/langdetect_backend.py
fastlangml/backends/langid_backend.py
fastlangml/backends/lingua_backend.py
fastlangml/backends/pycld3_backend.py
fastlangml/cache.py
fastlangml/cli/__init__.py
fastlangml/cli/main.py
fastlangml/codeswitching.py
fastlangml/config/__init__.py
fastlangml/context/__init__.py
fastlangml/context/conversation.py
fastlangml/context/disk_store.py
fastlangml/context/redis_store.py
fastlangml/detector.py
fastlangml/ensemble/__init__.py
fastlangml/ensemble/confusion.py
fastlangml/ensemble/voting.py
fastlangml/exceptions.py
fastlangml/hints/__init__.py
fastlangml/hints/dictionary.py
fastlangml/hints/persistence.py
fastlangml/normalize.py
fastlangml/preprocessing/__init__.py
fastlangml/preprocessing/name_filter.py
fastlangml/preprocessing/proper_noun_filter.py
fastlangml/preprocessing/script_filter.py
fastlangml/py.typed
fastlangml/result.py
fastlangml-1.1.0.dist-info/METADATA
fastlangml-1.1.0.dist-info/WHEEL
fastlangml-1.1.0.dist-info/entry_points.txt
fastlangml-1.1.0.dist-info/licenses/LICENSE
fastlangml-1.1.0.dist-info/RECORD
