Metadata-Version: 2.4
Name: fastlangml
Version: 1.1.0
Summary: FastLangML: High-accuracy language detection for chat, SMS & conversational text. Ensemble of FastText, Lingua, langdetect, CLD3 with context tracking, code-switching detection & 170+ languages.
License-Expression: MIT
License-File: LICENSE
Keywords: language-detection,language-identification,langid,detect-language,nlp,natural-language-processing,fasttext,fasttext-langdetect,lingua,lingua-language-detector,langdetect,pycld3,cld3,text-classification,conversational-ai,chatbot,multilingual,polyglot,code-switching,spanglish,ensemble,machine-learning,sms,chat,customer-service
Author: PRajan
Requires-Python: >=3.10,<4.0
Classifier: Development Status :: 5 - Production/Stable
Classifier: Intended Audience :: Developers
Classifier: Intended Audience :: Science/Research
Classifier: Operating System :: OS Independent
Classifier: Programming Language :: Python :: 3
Classifier: Programming Language :: Python :: 3.10
Classifier: Programming Language :: Python :: 3.11
Classifier: Programming Language :: Python :: 3.12
Classifier: Programming Language :: Python :: 3.13
Classifier: Topic :: Text Processing :: Linguistic
Classifier: Topic :: Scientific/Engineering :: Artificial Intelligence
Classifier: Topic :: Software Development :: Libraries :: Python Modules
Classifier: Typing :: Typed
Provides-Extra: all
Provides-Extra: diskcache
Provides-Extra: fastlangid
Provides-Extra: fasttext
Provides-Extra: fuzzy
Provides-Extra: langdetect
Provides-Extra: langid
Provides-Extra: lingua
Provides-Extra: pycld3
Provides-Extra: redis
Provides-Extra: spacy
Provides-Extra: toml
Requires-Dist: cachetools (>=5.0.0)
Requires-Dist: diskcache (>=5.0.0) ; extra == "all"
Requires-Dist: diskcache (>=5.0.0) ; extra == "diskcache"
Requires-Dist: fastlangid (>=1.0.11) ; extra == "all"
Requires-Dist: fastlangid (>=1.0.11) ; extra == "fastlangid"
Requires-Dist: fasttext-langdetect (>=1.0.5) ; extra == "all"
Requires-Dist: fasttext-langdetect (>=1.0.5) ; extra == "fasttext"
Requires-Dist: langdetect (>=1.0.9) ; extra == "all"
Requires-Dist: langdetect (>=1.0.9) ; extra == "langdetect"
Requires-Dist: langid (>=1.1.6) ; extra == "all"
Requires-Dist: langid (>=1.1.6) ; extra == "langid"
Requires-Dist: lingua-language-detector (>=2.0.0) ; extra == "all"
Requires-Dist: lingua-language-detector (>=2.0.0) ; extra == "lingua"
Requires-Dist: numpy (<2) ; extra == "all"
Requires-Dist: numpy (<2) ; extra == "fasttext"
Requires-Dist: pycld3 (>=0.22) ; extra == "all"
Requires-Dist: pycld3 (>=0.22) ; extra == "pycld3"
Requires-Dist: rapidfuzz (>=3.0.0) ; extra == "all"
Requires-Dist: rapidfuzz (>=3.0.0) ; extra == "fuzzy"
Requires-Dist: redis (>=4.0.0) ; extra == "all"
Requires-Dist: redis (>=4.0.0) ; extra == "redis"
Requires-Dist: spacy (>=3.5.0) ; extra == "all"
Requires-Dist: spacy (>=3.5.0) ; extra == "spacy"
Requires-Dist: tomli (>=2.0.0) ; python_version < "3.11"
Requires-Dist: tomli-w (>=1.0.0) ; extra == "toml"
Project-URL: Documentation, https://github.com/pnrajan/FastLangML#readme
Project-URL: Homepage, https://github.com/pnrajan/FastLangML
Project-URL: Issues, https://github.com/pnrajan/FastLangML/issues
Project-URL: Repository, https://github.com/pnrajan/FastLangML
